[
    {
        "杰克吉伦哈尔": "1",
        "夜行者": "1",
        "犯罪电影": "1",
        "惊悚片": "3",
        "电影混剪": "1",
        "动作片": "1",
        "程小东": "1",
        "仙侠电影": "1",
        "哪吒": "1",
        "孙悟空": "1",
        "大闹天宫": "1",
        "西游记之大圣归来": "1",
        "国产动画": "1",
        "搞笑": "8",
        "贝利叶一家": "1",
        "法国喜剧": "1",
        "温情": "1",
        "哈利波特": "2",
        "经典": "9",
        "成长": "1",
        "哈利•波特": "2",
        "魔幻片": "2",
        "冒险片": "1",
        "电影解说": "3",
        "欧美电影": "3",
        "奥斯卡最佳影片": "2",
        "老无所依": "1",
        "犯罪片": "1",
        "顶级反派": "1",
        "职场": "1",
        "Payday": "1",
        "科普": "2",
        "纪录片": "1",
        "徒手攀岩": "1",
        "美国工厂": "1",
        "2019平遥国际电影展": "1",
        "国产": "1",
        "蕃薯浇米": "1",
        "闽南话": "1",
        "贾樟柯": "1",
        "归亚蕾": "1",
        "李少红": "1",
        "杨贵媚": "1",
        "叶谦": "1",
        "周瑜": "1",
        "燃向混剪": "3",
        "剪辑": "1",
        "三国": "1",
        "踩点": "1",
        "大佛普拉斯": "1",
        "台湾电影": "1",
        "黑色幽默": "3",
        "华语": "1",
        "小怪兽": "1",
        "电影最TOP": "1",
        "平遥电影节": "1",
        "王者荣耀千灯会": "1",
        "电影剪辑": "3",
        "战争": "1",
        "昆汀塔伦蒂诺": "1",
        "低俗小说": "1",
        "暴力美学": "1",
        "毁三观": "1",
        "影评": "10",
        "犯罪": "5",
        "大卫芬奇": "2",
        "消失的爱人": "1",
        "惊悚": "2",
        "婚姻": "1",
        "电影盘点": "1",
        "飙车": "2",
        "致命ID": "1",
        "细读经典": "1",
        "悬疑": "1",
        "金凯瑞": "1",
        "喜剧": "3",
        "好莱坞": "3",
        "青春": "1",
        "心理学": "1",
        "伍迪艾伦": "1",
        "精神分析": "1",
        "历史": "1",
        "黑帮": "1",
        "禁酒令": "1",
        "徐峥": "2",
        "黄渤": "1",
        "无人区": "1",
        "宁浩": "1",
        "李连杰": "1",
        "赵文卓": "1",
        "关之琳": "1",
        "黄飞鸿": "1",
        "功夫片": "1",
        "2019bilibili年度影视大征稿": "2",
        "年终盘点": "3",
        "国产电影": "2",
        "流浪星球": "1",
        "吐槽": "3",
        "烂片": "1",
        "奥斯卡": "2",
        "艾玛沃特森": "1",
        "电影": "2",
        "爱情": "1",
        "小妇人": "1",
        "Timothée Chalamet": "1",
        "中国电影": "1",
        "复联4": "1",
        "引进片": "1",
        "寄生虫": "1",
        "影评杂谈": "2",
        "好莱坞往事": "1",
        "抗击肺炎大作战": "1",
        "武汉加油": "1",
        "新型冠状病毒": "1",
        "宁静": "1",
        "姜文": "1",
        "阳光灿烂的日子": "1",
        "夏雨": "1",
        "励志": "2",
        "拉塞尔克劳": "1",
        "美丽心灵": "1",
        "燃爆": "1",
        "勇士": "1",
        "热血": "1",
        "科幻": "1",
        "烧脑": "1",
        "吉伦哈尔": "1",
        "源代码": "1",
        "生化危机": "1",
        "游戏改编": "1",
        "雷片": "1",
        "钢琴家": "1",
        "人性": "2",
        "恐怖片": "1",
        "吓尿": "1",
        "高能预警": "1",
        "韩国电影": "1",
        "我不是药神": "1",
        "文牧野": "1",
        "费里尼": "1",
        "意大利电影": "1",
        "电影大师": "1",
        "导演盘点": "1",
        "楢山节考": "1",
        "残酷": "1",
        "今村昌平": "1",
        "日本电影": "1",
        "特朗普": "1",
        "川普": "1",
        "社交网络": "1",
        "盘点排行": "1",
        "香港电影": "2",
        "盘点": "1",
        "配角": "1",
        "爱国": "1",
        "正能量": "1",
        "中国": "1",
        "普通人": "1",
        "记录": "1",
        "高燃": "1",
        "催泪": "1",
        "疫情": "1",
        "张曼玉": "1",
        "黎明": "1",
        "甜蜜蜜": "1",
        "加勒比海盗": "1",
        "约翰尼德普": "1",
        "杰克船长": "1",
        "迪士尼": "1",
        "奇幻": "1",
        "狩猎": "1",
        "虐心": "1",
        "林青霞": "1",
        "周迅": "1",
        "女扮男装": "1",
        "香水": "1"
    }
]